lektor_twitter_embed/__init__.py
lektor_twitter_embed-0.2.0.dist-info/entry_points.txt
lektor_twitter_embed-0.2.0.dist-info/LICENSE
lektor_twitter_embed-0.2.0.dist-info/WHEEL
lektor_twitter_embed-0.2.0.dist-info/METADATA
lektor_twitter_embed-0.2.0.dist-info/RECORD
