Metadata-Version: 2.1
Name: lektor-twitter-embed
Version: 0.2.0
Summary: Lektor template filter to convert twitter links to embeds
Home-page: https://github.com/cigar-factory/lektor-twitter-embed
License: MIT
Keywords: Lektor plugin
Author: chris48s
Requires-Python: >=3.7,<4.0
Classifier: Environment :: Plugins
Classifier: Framework :: Lektor
Classifier: License :: OSI Approved :: MIT License
Classifier: Programming Language :: Python :: 3
Classifier: Programming Language :: Python :: 3.10
Classifier: Programming Language :: Python :: 3.7
Classifier: Programming Language :: Python :: 3.8
Classifier: Programming Language :: Python :: 3.9
Requires-Dist: lektor (>=3.0.0,<4.0.0)
Requires-Dist: requests (>=2.0.0,<3.0.0)
Project-URL: Repository, https://github.com/cigar-factory/lektor-twitter-embed
